iva_classification_demo/__init__.py
iva_classification_demo/class_computer.py
iva_classification_demo/comp_view.py
iva_classification_demo/main.py
iva_classification_demo-1.1.0.dist-info/METADATA
iva_classification_demo-1.1.0.dist-info/WHEEL
iva_classification_demo-1.1.0.dist-info/entry_points.txt
iva_classification_demo-1.1.0.dist-info/top_level.txt
iva_classification_demo-1.1.0.dist-info/RECORD
